Workbook
Name _SHR1: 'Personnaliser votre facture'!$D$30
Name _SHR2: 'Personnaliser votre facture'!$G$30
Name _Tax1: Facture!#REF!
Name _Tax2: Facture!$M$47
Name _Tax3: Facture!$M$49
Name _tax4: Facture!$M$49
Name boxes: Facture!$E$47:$E$48
Name CC: 'Personnaliser votre facture'!$G$22:$G$25
Name CCT: Facture!$H$49
Name CDB: 'Personnaliser votre facture'!$E$50
Name Country: 33
Name CS: 'Personnaliser votre facture'!$E$51
Name data1: Facture!$M$19
Name data10: Facture!$F$22
Name data11: Facture!#REF!
Name data12: Facture!#REF!
Name data13: Facture!#REF!
Name data14: Facture!#REF!
Name data15: Facture!#REF!
Name data16: Facture!#REF!
Name data17: Facture!#REF!
Name data18: Facture!#REF!
Name data19: Facture!#REF!
Name data2: Facture!$N$20
Name data20: Facture!#REF!
Name data21: Facture!#REF!
Name data22: Facture!#REF!
Name data23: Facture!#REF!
Name data24: Facture!#REF!
Name data25: Facture!#REF!
Name data26: Facture!#REF!
Name data27: Facture!#REF!
Name data28: Facture!#REF!
Name data29: Facture!#REF!
Name data3: Facture!$N$21
Name data30: Facture!#REF!
Name data31: Facture!#REF!
Name data32: Facture!#REF!
Name data33: Facture!#REF!
Name data34: Facture!#REF!
Name data35: Facture!#REF!
Name data36: Facture!#REF!
Name data37: Facture!#REF!
Name data38: Facture!#REF!
Name data39: Facture!#REF!
Name data4: Facture!$N$22
Name data40: Facture!#REF!
Name data41: Facture!#REF!
Name data42: Facture!#REF!
Name data43: Facture!#REF!
Name data44: Facture!#REF!
Name data45: Facture!#REF!
Name data46: Facture!#REF!
Name data47: Facture!$E$25
Name data48: Facture!$F$25
Name data49: Facture!$M$25
Name data5: Facture!$E$19
Name data50: Facture!#REF!
Name data51: Facture!#REF!
Name data52: Facture!#REF!

Sheet AutoOpen Stub Data

Sheet Personnaliser votre facture
D4: PERSONNALISER VOTRE FACTURE
G7: Placez votre point
G8: ICI pour un conseil utile
D10: Tapez les informations sur la société...
D12: Nom | E12: GAMESTREAM ATLAS ORGANISME DE FORMATION N° D'AGREMENT : 01 069 11 | F12: Numéro de téléphone
D13: Adresse | E13: 4 RUE DU CAIRE 1001 TUNIS | F13: Numéro de télécopie
D14: Code postal | E14: TEL: 71 258108
D15: Ville | E15: FAX : 71 259346
D16: Pays
D19: Spécifiez les informations par défaut…
E21: Taux de TVA à appliquer | G21: Cartes de crédit acceptées
D22: 1 | E22: 0.1
D23: 2 | E23: 0.18
D24: 3 | E24: 0.29
F27: TIMBRE FISCAL | G27: 0.2
D30: FALSE | E30: Partage de la numérotation du | F30: Emplacement
E31: modèle de facture sur le réseau | F31: du compteur
E33: Base de données de l'Assistant Modèle | F33: =LOWER(TemplateInformation!B3) -> c:\program files\microsoft office\office\macrolib\factbd.xls
D36: Informations sur la mise en forme
E47: 33
E48: 0
E49: FALSE
E50: FALSE
E51: Facture
E52: Facture

Sheet Facture
M9: TUNISIE
M10: http://www.camp.it
J15: OFFER PRICE 2023 4786
D19: Nom | E19: Société d’Articles Hygiéniques (SAH) | L19: Date | M19: 45086
D20: Adresse
D21: Code postal | F21: Ville | G21: mjez elbab | I21: Pays | J21: tunisie | L21: Responsable | M21: Mme Najoua
D22: Téléphone | E22: fax: | L22: MF
D24: Référence | E24: Quantité | F24: Description | L24: Code T.V.A. | M24: P.U HT | N24: Montant
N25: =IF(E25<>"",E25*M25,"")
E26: 1 | F26: Sangle de levage et de manutention
A27: f | F27: conforme à EN 1492-1 + A1 | N27: =IF(E27<>"",E27*M27,"")
F28: CHARGE 2TONNES | N28: =IF(E28<>"",E28*M28,"")
N29: =IF(E29<>"",E29*M29,"")
E30: 2 | F30: 2M | M30: 45 | N30: =IF(E30<>"",E30*M30,"") -> 90
E31: 2 | F31: 4M | M31: 76 | N31: =IF(E31<>"",E31*M31,"") -> 152
N32: =IF(E32<>"",E32*M32,"")
N33: =IF(E33<>"",E33*M33,"")
N34: =IF(E34<>"",E34*M34,"")
N35: =IF(E35<>"",E35*M35,"")
N36: =IF(E36<>"",E36*M36,"")
N37: =IF(E37<>"",E37*M37,"")
N38: =IF(E38<>"",E38*M38,"")
N39: =IF(E39<>"",E39*M39,"")
N40: =IF(E41<>"",E41*M40,"")
N41: =IF(E42<>"",E42*M41,"")
N42: =IF(E43<>"",E43*M42,"")
N43: =IF(E44<>"",E44*M43,"")
N44: =IF(E45<>"",E45*M44,"")
M45: Total H.T. | N45: =SUM(N25:N44) -> 242
E46: Paiement à la livraison | M46: TIMBRE FISCAL | N46: 0.6
F47: Comptant | M47: TVA:19% | N47: =N45*0.19 -> 45.98
F48: Chèque | M48: Total T.T.C. | N48: =+N45+N46+N47 -> 288.58
E49: 1
K53: SIGNATURE :

Sheet Patientez un instant...

Sheet TemplateInformation
A1: AutoTemplateWizardDONTMESSWITHIT
A2: Database Type: | B2: Excel 5.0
A3: Database Location: | B3: C:\PROGRAM FILES\MICROSOFT OFFICE\OFFICE\MACROLIB\factbd.xls
A4: Reserved
A5: Number of Tables: | B5: 1
A6: 1 | B6: Table Name: | C6: France | D6: Number of Fields: | E6: 10 | G6: -1383939328
A7: Field Name: | B7: Facture N° | C7: Date | D7: Nom | E7: Adresse | F7: Code postal | G7: Ville | H7: Pays | I7: Téléphone | J7: TOTAL | K7: Responsable
A8: Refers To: | B8: =Facture!$N$11 | C8: =Facture!$M$19 -> 45086 | D8: =Facture!$E$19 -> Société d’Articles Hygiéniques (SAH) | E8: =Facture!$E$20 -> 0 | F8: =Facture!$E$21 -> 0 | G8: =Facture!$G$21 -> mjez elbab | H8: =Facture!$J$21 -> tunisie | I8: =Facture!$E$22 -> fax: | J8: =Facture!$N$48 -> 288.58 | K8: =Facture!$M$21 -> Mme Najoua
A9: Reserved
G10: -1261995520
G14: -462007040

Sheet Macros
