Workbook
Name _SHR1: 'Personnaliser votre facture'!$D$30
Name _SHR2: 'Personnaliser votre facture'!$G$30
Name _Tax1: Facture!$L$56
Name _Tax2: Facture!#REF!
Name _Tax3: Facture!#REF!
Name _tax4: Facture!#REF!
Name boxes: Facture!$E$56:$E$57
Name CC: 'Personnaliser votre facture'!$G$22:$G$25
Name CCT: Facture!$H$59
Name CDB: 'Personnaliser votre facture'!$E$50
Name Country: 33
Name CS: 'Personnaliser votre facture'!$E$51
Name data1: Facture!$L$23
Name data10: Facture!$F$26
Name data11: Facture!$E$31
Name data12: Facture!$F$31
Name data13: Facture!$L$31
Name data14: Facture!$E$32
Name data15: Facture!$F$32
Name data16: Facture!$L$32
Name data17: Facture!#REF!
Name data18: Facture!#REF!
Name data19: Facture!#REF!
Name data2: Facture!$M$24
Name data20: Facture!#REF!
Name data21: Facture!#REF!
Name data22: Facture!#REF!
Name data23: Facture!#REF!
Name data24: Facture!#REF!
Name data25: Facture!#REF!
Name data26: Facture!#REF!
Name data27: Facture!#REF!
Name data28: Facture!#REF!
Name data29: Facture!#REF!
Name data3: Facture!$M$25
Name data30: Facture!#REF!
Name data31: Facture!#REF!
Name data32: Facture!#REF!
Name data33: Facture!#REF!
Name data34: Facture!#REF!
Name data35: Facture!#REF!
Name data36: Facture!#REF!
Name data37: Facture!#REF!
Name data38: Facture!#REF!
Name data39: Facture!#REF!
Name data4: Facture!$M$26
Name data40: Facture!#REF!
Name data41: Facture!#REF!
Name data42: Facture!#REF!
Name data43: Facture!#REF!
Name data44: Facture!#REF!
Name data45: Facture!#REF!
Name data46: Facture!#REF!
Name data47: Facture!#REF!
Name data48: Facture!#REF!
Name data49: Facture!#REF!
Name data5: Facture!$E$23
Name data50: Facture!#REF!
Name data51: Facture!#REF!
Name data52: Facture!#REF!

Sheet AutoOpen Stub Data

Sheet Personnaliser votre facture
D4: PERSONNALISER VOTRE FACTURE
G7: Placez votre point
G8: ICI pour un conseil utile
D10: Tapez les informations sur la société...
D12: Nom | E12: GAMESTREAM ATLAS ORGANISME DE FORMATION N° D'AGREMENT : 01 069 11 | F12: Numéro de téléphone
D13: Adresse | E13: 4 RUE DU CAIRE 1001 TUNIS | F13: Numéro de télécopie
D14: Code postal | E14: TEL: 71 258108
D15: Ville | E15: FAX : 71 259346
D16: Pays
D19: Spécifiez les informations par défaut…
E21: Taux de TVA à appliquer | G21: Cartes de crédit acceptées
D22: 1 | E22: 0.1
D23: 2 | E23: 0.18
D24: 3 | E24: 0.29
F27: TIMBRE FISCAL | G27: 0.2
D30: FALSE | E30: Partage de la numérotation du | F30: Emplacement
E31: modèle de facture sur le réseau | F31: du compteur
E33: Base de données de l'Assistant Modèle | F33: =LOWER(TemplateInformation!B3) -> c:\program files\microsoft office\office\macrolib\factbd.xls
D36: Informations sur la mise en forme
E47: 33
E48: 0
E49: FALSE
E50: FALSE
E51: Facture
E52: Facture

Sheet Facture
L15: DEVIS N°2025-199
D23: Nom: | E23: LEPIDOR | K23: Date: | L23: 45698
D24: Adresse:
D25: Code postal: | F25: Ville: | G25: SOUSSE | I25: PAYS | J25: TN | K25: Responsable: MME SAHAR
A26: 71 | D26: Téléphone: | K26: MF : | L26: 4586 H A M 000
D30: Référence | E30: NOMBRE | F30: Description | L30: P.U. | M30: Montant
M31: =IF(E31<>"",E31*L31,"")
F32: FORMATION THEORIQUE ET PRATIQUE : | M32: =IF(E32<>"",E32*L32,"")
F33: HABILITATION:
E35: 5 | F35: TRAVAIL EN HAUTEUR | L35: 250 | M35: =IF(E35<>"",E35*L35,"") -> 1250
E36: 5 | F36: ESPACES CONFINES | L36: 250 | M36: =IF(E36<>"",E36*L36,"") -> 1250
F38: PRIX PAR PARTICIPANT | M38: =IF(E38<>"",E38*L38,"")
M39: =IF(E39<>"",E39*L39,"")
F40: NB : Nous avons gardé pour vous les mêmes prix de l'année dernière en récompense à votre fidélité
F41: COMPRENANT : | M41: =IF(E41<>"",E41*L41,"")
F42: 1- PRESTATION DE L'ANIMATEUR | M42: =IF(E42<>"",E42*L42,"")
F43: 2- MISE A DISPOSITION DE MATERIEL | M43: =IF(E43<>"",E43*L43,"")
F44: DE DEMONSTRATION PRATIQUE POUR | M44: =IF(E44<>"",E44*L44,"")
F45: LES STAGIAIRES . | M45: =IF(E45<>"",E45*L45,"")
F46: 3- REMISE D'UNE DOCUMENTATION | M46: =IF(E46<>"",E46*L46,"")
M47: =IF(E47<>"",E47*L47,"")
F48: N.B: | M48: =IF(E48<>"",E48*L48,"")
F49: LE STAGE EST SANCTIONNE PAR UN VISA | M49: =IF(E49<>"",E49*L49,"")
F50: VALABLE 3ANS | M50: =IF(E50<>"",E50*L50,"")
M51: =IF(E51<>"",E51*L51,"")
M52: =IF(E52<>"",E52*L52,"")
M53: =IF(E53<>"",E53*L53,"")
L54: Total H.T. | M54: =SUM(M34:M53) -> 2500
F55: Comptant | L55: TIMBRE FISCAL | M55: 1
F56: Virement | L56: T.V.A 19% | M56: =M54*0.19 -> 475
F57: Chèque | L57: Total T.T.C. | M57: =M54+M56+M55 -> 2976
E58: 2 | L58: SIGNATURE & CACHET
D59: RIB : 10 000 000 081951 8 78890
D60: STB THAMEUR
A61: 4,RUE DU CAIRE 1001 TUNIS- Tunisie Tél : (216).71 258 108 Fax : (216).71 259 346 RDC:B159472001 / MF:778013 ZMA 000 Mail:gamestream@planet.tn//gamestream.formation@gmail.com

Sheet Patientez un instant...

Sheet TemplateInformation
A1: AutoTemplateWizardDONTMESSWITHIT
A2: Database Type: | B2: Excel 5.0
A3: Database Location: | B3: C:\PROGRAM FILES\MICROSOFT OFFICE\OFFICE\MACROLIB\factbd.xls
A4: Reserved
A5: Number of Tables: | B5: 1
A6: 1 | B6: Table Name: | C6: France | D6: Number of Fields: | E6: 10 | G6: -727923968
A7: Field Name: | B7: Facture N° | C7: Date | D7: Nom | E7: Adresse | F7: Code postal | G7: Ville | H7: Pays | I7: Téléphone | J7: TOTAL | K7: Responsable
A8: Refers To: | B8: =Facture!$M$11 | C8: =Facture!$L$23 -> 45698 | D8: =Facture!$E$23 -> LEPIDOR | E8: =Facture!$E$24 -> 0 | F8: =Facture!$E$25 -> 0 | G8: =Facture!$G$25 -> SOUSSE | H8: =Facture!$J$25 -> TN | I8: =Facture!$E$26 -> 0 | J8: =Facture!$M$57 -> 2976 | K8: =Facture!$L$25 -> 0
A9: Reserved
G10: 324499967
G14: 1194546431

Sheet Macros
